simplesat/__init__.py
simplesat/_version.py
simplesat/compute_dependencies.py
simplesat/dependency_solver.py
simplesat/errors.py
simplesat/package.py
simplesat/pool.py
simplesat/repository.py
simplesat/request.py
simplesat/rules_generator.py
simplesat/test_utils.py
simplesat/transaction.py
simplesat/constraints/__init__.py
simplesat/constraints/constraint_modifiers.py
simplesat/constraints/kinds.py
simplesat/constraints/multi.py
simplesat/constraints/package_parser.py
simplesat/constraints/parser.py
simplesat/constraints/requirement.py
simplesat/constraints/tests/__init__.py
simplesat/constraints/tests/test_constraint_modifiers.py
simplesat/constraints/tests/test_multi.py
simplesat/constraints/tests/test_package_parser.py
simplesat/constraints/tests/test_parser.py
simplesat/constraints/tests/test_requirement.py
simplesat/examples/__init__.py
simplesat/examples/van_der_waerden.py
simplesat/sat/__init__.py
simplesat/sat/assignment_set.py
simplesat/sat/clause.py
simplesat/sat/minisat.py
simplesat/sat/policy/__init__.py
simplesat/sat/policy/policy.py
simplesat/sat/policy/policy_logger.py
simplesat/sat/policy/undetermined_clause_policy.py
simplesat/sat/tests/__init__.py
simplesat/sat/tests/test_assignment_set.py
simplesat/sat/tests/test_minisat.py
simplesat/sat/tests/test_minisat_problems.py
simplesat/test_data/__init__.py
simplesat/tests/__init__.py
simplesat/tests/broken_metadata_self_conflict.yaml
simplesat/tests/complex_numpy_downgrade.yaml
simplesat/tests/conflict_by_provides.yaml
simplesat/tests/constraint_modifiers.yaml
simplesat/tests/directly_implied_solution.yaml
simplesat/tests/epd_free_upgrade.yaml
simplesat/tests/epd_full_conflict.yaml
simplesat/tests/epd_full_upgrade.yaml
simplesat/tests/explicit_conflict.yaml
simplesat/tests/installed_pkg_missing_in_remote.yaml
simplesat/tests/installed_pkg_missing_in_remote_not_requested.yaml
simplesat/tests/ipython.yaml
simplesat/tests/ipython_downgrade.yaml
simplesat/tests/ipython_upgrade.yaml
simplesat-0.9.2.dist-info/METADATA
simplesat-0.9.2.dist-info/WHEEL
simplesat-0.9.2.dist-info/top_level.txt
simplesat-0.9.2.dist-info/RECORD
