Metadata-Version: 2.1
Name: simplesat
Version: 0.9.2
Summary: Prototype for SAT-based dependency handling. This is a work in progress, do not expect any API not to change at this point.
Home-page: https://github.com/enthought/sat-solver
Author: Enthought Inc.
Author-email: info@enthought.com
License: BSD-3-Clause
Classifier: Programming Language :: Python :: 3
Classifier: Programming Language :: Python :: 3.8
Classifier: Programming Language :: Python :: 3.9
Classifier: Programming Language :: Python :: 3.10
Classifier: Programming Language :: Python :: 3.11
Classifier: Programming Language :: Python :: 3.12
Requires-Python: >=3.8
